setup.py
ret_distributions/Binomialdistribution.py
ret_distributions/Gaussiandistribution.py
ret_distributions/Generaldistribution.py
ret_distributions/__init__.py
ret_distributions.egg-info/PKG-INFO
ret_distributions.egg-info/SOURCES.txt
ret_distributions.egg-info/dependency_links.txt
ret_distributions.egg-info/not-zip-safe
ret_distributions.egg-info/top_level.txt